pidlock.py
pidlock-3.0.2.dist-info/LICENSE.txt
pidlock-3.0.2.dist-info/METADATA
pidlock-3.0.2.dist-info/WHEEL
pidlock-3.0.2.dist-info/entry_points.txt
pidlock-3.0.2.dist-info/top_level.txt
pidlock-3.0.2.dist-info/RECORD
