Metadata-Version: 2.1
Name: pidlock
Version: 3.0.2
Summary: Simple PID based locking for cronjobs, UNIX scripts or python programs
Home-page: https://github.com/keiranmraine/pidlock
Author: Keiran Raine
Author-email: keiranmraine@gmail.com
License: MIT
Download-URL: https://github.com/keiranmraine/pidlock/archive/v3.0.2.tar.gz
Keywords: PID Based File Locking
Platform: UNKNOWN
Classifier: Development Status :: 5 - Production/Stable
Classifier: Intended Audience :: Developers
Classifier: Intended Audience :: Information Technology
Classifier: Intended Audience :: System Administrators
Classifier: License :: OSI Approved :: MIT License
Classifier: Natural Language :: English
Classifier: Programming Language :: Python :: 3
Classifier: Topic :: Utilities
Classifier: Operating System :: MacOS
Classifier: Operating System :: POSIX
License-File: LICENSE.txt
Requires-Dist: psutil (~=5.9.1)
